MANIFEST.in
setup.py
apitest_harness/__init__.py
apitest_harness/license.txt
apitest_harness/requirements.txt
apitest_harness/setup.cfg
apitest_harness.egg-info/PKG-INFO
apitest_harness.egg-info/SOURCES.txt
apitest_harness.egg-info/dependency_links.txt
apitest_harness.egg-info/not-zip-safe
apitest_harness.egg-info/requires.txt
apitest_harness.egg-info/top_level.txt
apitest_harness/logs/logfile.log
apitest_harness/report/LSCC_APIVerification_v3_report_21_03_2023-05_04_55_PM
apitest_harness/report/LSCC_APIVerification_v3_report_21_03_2023-05_04_55_PM.xlsx
apitest_harness/source/APIVerification.xlsx
apitest_harness/source/Finmagix_testcases.xlsx
apitest_harness/source/testcase_json.JSON
apitest_harness/src/Ls_regression.py
apitest_harness/src/__init__.py
apitest_harness/src/generatejson.py
apitest_harness/src/testharness.py