Metadata-Version: 2.1
Name: apitest-harness
Version: 0.1
Summary: API Testing Framework
Author: Bytes Arena Solution Pvt Ltd
